{
  "id": "item_table",
  "type": "SharedSlice",
  "name": "ItemTable",
  "description": "ItemTable",
  "variations": [
    {
      "id": "default",
      "name": "Default",
      "docURL": "...",
      "version": "initial",
      "description": "Default",
      "imageUrl": "",
      "primary": {
        "main_title": {
          "type": "Text",
          "config": {
            "label": "Main Title",
            "placeholder": ""
          }
        },
        "subtitle": {
          "type": "Text",
          "config": {
            "label": "Subtitle",
            "placeholder": ""
          }
        },
        "background_image": {
          "type": "Image",
          "config": {
            "label": "Background Image",
            "constraint": {},
            "thumbnails": []
          }
        },
        "background_color": {
          "type": "Select",
          "config": {
            "label": "Background Color",
            "placeholder": "",
            "options": [
              "White",
              "Cream",
              "Green",
              "Gray"
            ],
            "default_value": "White"
          }
        },
        "item": {
          "type": "Group",
          "config": {
            "label": "Item",
            "repeat": true,
            "fields": {
              "title": {
                "type": "Text",
                "config": {
                  "label": "Title",
                  "placeholder": ""
                }
              },
              "text": {
                "type": "StructuredText",
                "config": {
                  "label": "Text",
                  "placeholder": "",
                  "allowTargetBlank": true,
                  "multi": "paragraph,preformatted,heading1,heading2,heading3,heading4,heading5,heading6,strong,em,hyperlink,image,embed,list-item,o-list-item,rtl"
                }
              },
              "image": {
                "type": "Image",
                "config": {
                  "label": "Image",
                  "constraint": {},
                  "thumbnails": []
                }
              }
            }
          }
        }
      },
      "items": {}
    }
  ]
}